{
  "$schema": "https://json-structure.org/meta/core/v0/#",
  "$id": "https://raw.githubusercontent.com/api-evangelist/amazon-mediaconnect/refs/heads/main/json-structure/mediaconnect-api-grant-flow-entitlements-request-structure.json",
  "name": "GrantFlowEntitlementsRequest",
  "type": "object",
  "description": "A request to grant entitlements on a flow.",
  "properties": {
    "Entitlements": {
      "allOf": [
        {
          "$ref": "#/components/schemas/__listOfGrantEntitlementRequest"
        },
        {
          "xml": {
            "name": "entitlements"
          },
          "description": "The list of entitlements that you want to grant."
        }
      ]
    }
  },
  "required": [
    "Entitlements"
  ]
}